rin_pytorch/__init__.py
rin_pytorch/attend.py
rin_pytorch/rin_pytorch.py
RIN_pytorch-0.7.10.dist-info/LICENSE
RIN_pytorch-0.7.10.dist-info/METADATA
RIN_pytorch-0.7.10.dist-info/WHEEL
RIN_pytorch-0.7.10.dist-info/top_level.txt
RIN_pytorch-0.7.10.dist-info/RECORD
