Metadata-Version: 2.1
Name: RIN-pytorch
Version: 0.7.10
Summary: RIN - Recurrent Interface Network - Pytorch
Home-page: https://github.com/lucidrains/RIN-pytorch
Author: Phil Wang
Author-email: lucidrains@gmail.com
License: MIT
Keywords: artificial intelligence,deep learning,attention mechanism,denoising diffusion,image and video generation
Classifier: Development Status :: 4 - Beta
Classifier: Intended Audience :: Developers
Classifier: Topic :: Scientific/Engineering :: Artificial Intelligence
Classifier: License :: OSI Approved :: MIT License
Classifier: Programming Language :: Python :: 3.6
License-File: LICENSE
Requires-Dist: accelerate
Requires-Dist: beartype
Requires-Dist: ema-pytorch
Requires-Dist: einops >=0.6
Requires-Dist: pillow
Requires-Dist: torch >=1.12.0
Requires-Dist: torchvision
Requires-Dist: tqdm
